moblabpy/__init__.py
moblabpy/moblabgui.py
moblabpy/moblabpy.py
moblabpy-0.0.2.dist-info/LICENSE
moblabpy-0.0.2.dist-info/METADATA
moblabpy-0.0.2.dist-info/WHEEL
moblabpy-0.0.2.dist-info/top_level.txt
moblabpy-0.0.2.dist-info/RECORD
