Metadata-Version: 2.1
Name: moblabpy
Version: 0.0.2
Summary: A module that allow users to stimluate communcation system via their own device
Home-page: https://github.com/moblabpy/moblabpy
Author: Moblabpy Official
Author-email: moblabpy@gmail.com
License: UNKNOWN
Project-URL: Code, https://github.com/moblabpy/moblabpy
Project-URL: Documentation, https://moblabpy.readthedocs.io/en/latest/
Keywords: BYOD,COMMUNICATION
Platform: UNKNOWN
Classifier: Development Status :: 3 - Alpha
Classifier: Intended Audience :: Education
Classifier: Intended Audience :: Developers
Classifier: Topic :: Communications
Classifier: Topic :: Education
Classifier: License :: OSI Approved :: MIT License
Classifier: Programming Language :: Python :: 3
Classifier: Programming Language :: Python :: 3.8
Classifier: Programming Language :: Python :: 3.9
Requires-Python: >=3.6
Requires-Dist: numpy
Requires-Dist: segno
Requires-Dist: pyzbar
Requires-Dist: Pillow
Requires-Dist: opencv-python
